galaxy_object_detection_core/GalaxyObjectDetector.py
galaxy_object_detection_core/__init__.py
galaxy_object_detection_core/models/yolov8s-world.pt
galaxy_object_detection_core/tools/Timer.py
galaxy_object_detection_core/tools/__init__.py
galaxy_object_detection_core-0.1.5.dist-info/licenses/LICENCE
galaxy_object_detection_core-0.1.5.dist-info/METADATA
galaxy_object_detection_core-0.1.5.dist-info/WHEEL
galaxy_object_detection_core-0.1.5.dist-info/top_level.txt
galaxy_object_detection_core-0.1.5.dist-info/RECORD
