Metadata-Version: 2.4
Name: galaxy-object-detection-core
Version: 0.1.5
Summary: YOLO-based object detection system for various industries
Home-page: https://github.com/muhammadhaerul/Galaxy-Object-Detection-Core
Author: @muhammadhaerul.25
License: Proprietary License
Classifier: Programming Language :: Python :: 3
Classifier: License :: OSI Approved :: MIT License
Classifier: Operating System :: OS Independent
Requires-Python: >=3.10
License-File: LICENCE
Requires-Dist: ultralytics==8.3.146
Dynamic: author
Dynamic: classifier
Dynamic: description
Dynamic: description-content-type
Dynamic: home-page
Dynamic: license
Dynamic: license-file
Dynamic: requires-dist
Dynamic: requires-python
Dynamic: summary
